Metadata-Version: 2.1
Name: hf-tap-filesanywhere
Version: 0.0.1
Summary: `tap-filesanywhere` is a Singer tap for FilesAnywhere, built with the Meltano Singer SDK.
License: Apache-2.0
Keywords: ELT,FilesAnywhere
Author: Tanner Euston
Author-email: teuston@healthfirst.org
Requires-Python: >=3.8,<4.0
Classifier: Intended Audience :: Developers
Classifier: License :: OSI Approved :: Apache Software License
Classifier: Operating System :: OS Independent
Classifier: Programming Language :: Python :: 3
Classifier: Programming Language :: Python :: 3.8
Classifier: Programming Language :: Python :: 3.9
Classifier: Programming Language :: Python :: 3.10
Classifier: Programming Language :: Python :: 3.11
Classifier: Programming Language :: Python :: 3.12
Provides-Extra: s3
Requires-Dist: azure-storage-blob (>=12.19.1,<13.0.0)
Requires-Dist: boto3 (>=1.34.67,<2.0.0)
Requires-Dist: fs-s3fs (>=1.1.1,<1.2.0) ; extra == "s3"
Requires-Dist: google (>=3.0.0,<4.0.0)
Requires-Dist: google-cloud (>=0.34.0,<0.35.0)
Requires-Dist: importlib-resources (==6.1.*) ; python_version < "3.9"
Requires-Dist: openpyxl (>=3.1.2,<4.0.0)
Requires-Dist: pytz (>=2024.1,<2025.0)
Requires-Dist: requests (>=2.31.0,<3.0.0)
Requires-Dist: singer-sdk[faker] (>=0.36.1,<0.37.0)
Requires-Dist: smart-open (>=7.0.1,<8.0.0)
Requires-Dist: xlrd (>=2.0.1,<3.0.0)
